mcp_server_rds_mysql/__init__.py
mcp_server_rds_mysql/config.py
mcp_server_rds_mysql/server.py
rds_mysql_mcp_server-0.1.0.dist-info/METADATA
rds_mysql_mcp_server-0.1.0.dist-info/WHEEL
rds_mysql_mcp_server-0.1.0.dist-info/entry_points.txt
rds_mysql_mcp_server-0.1.0.dist-info/top_level.txt
rds_mysql_mcp_server-0.1.0.dist-info/RECORD
